tscircuit/__init__.py
tscircuit-0.0.1.dist-info/METADATA
tscircuit-0.0.1.dist-info/WHEEL
tscircuit-0.0.1.dist-info/licenses/LICENSE
tscircuit-0.0.1.dist-info/RECORD
