Metadata-Version: 2.4
Name: tscircuit
Version: 0.0.1
Summary: tscircuit Python package
Project-URL: Homepage, https://github.com/tscircuit/tscircuit
Project-URL: Repository, https://github.com/tscircuit/tscircuit
Author: tscircuit
License-Expression: MIT
License-File: LICENSE
Classifier: Development Status :: 3 - Alpha
Classifier: Intended Audience :: Developers
Classifier: License :: OSI Approved :: MIT License
Classifier: Programming Language :: Python :: 3
Classifier: Programming Language :: Python :: 3.8
Classifier: Programming Language :: Python :: 3.9
Classifier: Programming Language :: Python :: 3.10
Classifier: Programming Language :: Python :: 3.11
Classifier: Programming Language :: Python :: 3.12
Requires-Python: >=3.8
